{
	"Стас":"Всегда внимательно выслушает, даст мотивацию к действию и глубинный взгляд со стороны.",
	"Линда":"Поможет пройти самые сложные переживания комфортно, не заставляя делать то, к чему ты не готов.",
	"Залина":"Знает не понаслышке, каково это – заглянуть в самую глубь себя и «остаться в живых».",
	"Аза":"Чётко определит, куда следует обратить внимание и укажет направление.",
	"Лена":"Поможет пройти через любые «ураганы» эмоций, потому что сама не раз в них бывала.",
	"Маша":"Умеет пропустить через себя любую боль и другие чувства. Готова отдать всю любовь, которая у неё есть.",
	"Аслан":"Легко смотрит любым страхам в глаза. Создает теплую атмосферу принятия.",
	"Дима":"Его способность принимать и быть чутким помогают каждому раскрыться и дойти до сути.",
	"Катя":"Поможет не застрять, не сдаться и не сделать ни шагу назад.",
	"Вероника":"Поможет увидеть возможности там, где, кажется, уже все потеряно."

}